nr/__init__.py
nr/sumtype.py
nr.sumtype-0.0.5.dist-info/LICENSE.txt
nr.sumtype-0.0.5.dist-info/METADATA
nr.sumtype-0.0.5.dist-info/WHEEL
nr.sumtype-0.0.5.dist-info/top_level.txt
nr.sumtype-0.0.5.dist-info/zip-safe
nr.sumtype-0.0.5.dist-info/RECORD
