Metadata-Version: 2.1
Name: nr.sumtype
Version: 0.0.5
Summary: Sumtypes in Python.
Home-page: https://git.niklasrosenstein.com/NiklasRosenstein/nr
Author: Niklas Rosenstein
Author-email: rosensteinniklas@gmail.com
License: MIT
Platform: UNKNOWN
Requires-Dist: nr.metaclass (<1.0.0,>=0.0.4)
Requires-Dist: nr.stream (<1.0.0,>=0.0.2)
